<?xml version="1.0" encoding="utf-8" ?>
<Levels>
	<Level>
		<Room>
			<name>Room1</name>
			<sheet>room1</sheet>
			<up></up>
			<down></down>
			<left></left>
			<right>room2</right>

			<objects>
				<data>
					<type>Link</type>
					<type2></type2>
					<row>0</row>
					<column>0</column>
				</data>
				<data>
					<type>Item</type>
					<type2>Angel</type2>
					<row>0</row>
					<column>2</column>
				</data>
				<data>
					<type>Enemy</type>
					<type2>Moblin</type2>
					<row>2</row>
					<column>0</column>
				</data>
				<data>
					<type>Block</type>
					<type2>Base</type2>
					<row>3</row>
					<column>0</column>
				</data>
			</objects>
		</Room>
	</Level>
</Levels>
